blitz_player/__init__.py
blitz_player/player.py
blitz_player-0.1.1.dist-info/LICENSE
blitz_player-0.1.1.dist-info/METADATA
blitz_player-0.1.1.dist-info/WHEEL
blitz_player-0.1.1.dist-info/entry_points.txt
blitz_player-0.1.1.dist-info/top_level.txt
blitz_player-0.1.1.dist-info/RECORD
