Metadata-Version: 2.1
Name: blitz-player
Version: 0.1.1
Summary: A CLI YouTube Music player
Home-page: https://github.com/blitzjb/blitz-player
Author: BlitzJB
Author-email: blitz04.dev@gmail.com
Classifier: Programming Language :: Python :: 3
Classifier: License :: OSI Approved :: MIT License
Classifier: Operating System :: OS Independent
Requires-Python: >=3.6
License-File: LICENSE
Requires-Dist: ytmusicapi
Requires-Dist: yt-dlp
Requires-Dist: python-vlc
Requires-Dist: appdirs
